cemc_plots_kit/__init__.py
cemc_plots_kit/__main__.py
cemc_plots_kit/_version.py
cemc_plots_kit/config.py
cemc_plots_kit/draw.py
cemc_plots_kit/job.py
cemc_plots_kit/logger.py
cemc_plots_kit/task.py
cemc_plots_kit/plots/__init__.py
cemc_plots_kit/plots/height_500_mslp.py
cemc_plots_kit/plots/height_500_wind_850.py
cemc_plots_kit/plots/prep_24h.py
cemc_plots_kit/plots/radar_reflectivity.py
cemc_plots_kit/plots/rain_12h_wind_10m.py
cemc_plots_kit/plots/rain_1h_wind_10m.py
cemc_plots_kit/plots/rain_24h.py
cemc_plots_kit/plots/rain_24h_wind_10m.py
cemc_plots_kit/plots/rain_3h_wind_10m.py
cemc_plots_kit/plots/rain_6h_wind_10m.py
cemc_plots_kit/plots/t_2m.py
cemc_plots_kit/plots/wind_10m.py
cemc_plots_kit/source/__init__.py
cemc_plots_kit-2024.10.0.dist-info/LICENSE
cemc_plots_kit-2024.10.0.dist-info/METADATA
cemc_plots_kit-2024.10.0.dist-info/WHEEL
cemc_plots_kit-2024.10.0.dist-info/top_level.txt
cemc_plots_kit-2024.10.0.dist-info/RECORD
